README.md
.githooks/README.md
docs/README.md
funannotate2/__init__.py
funannotate2/__main__.py
funannotate2/abinitio.py
funannotate2/align.py
funannotate2/annotate.py
funannotate2/clean.py
funannotate2/config.py
funannotate2/database.py
funannotate2/downloads.json
funannotate2/evm.py
funannotate2/fastx.py
funannotate2/genbank.py
funannotate2/help_formatter.py
funannotate2/install.py
funannotate2/interlap.py
funannotate2/log.py
funannotate2/name_cleaner.py
funannotate2/predict.py
funannotate2/search.py
funannotate2/train.py
funannotate2/utilities.py
funannotate2/resources/extrinsic.E.XNT.RM.cfg
funannotate2-25.7.1.dist-info/METADATA
funannotate2-25.7.1.dist-info/WHEEL
funannotate2-25.7.1.dist-info/entry_points.txt
funannotate2-25.7.1.dist-info/licenses/LICENSE
funannotate2-25.7.1.dist-info/RECORD
