Metadata-Version: 2.4
Name: funannotate2
Version: 25.7.1
Summary: Funannotate2: eukarytoic genome annotation pipeline
Project-URL: Homepage, https://github.com/nextgenusfs/funannotate2
Project-URL: Repository, https://github.com/nextgenusfs/funannotate2.git
Author-email: Jon Palmer <nextgenusfs@gmail.com>
License: BSD 2-Clause License
License-File: LICENSE
Keywords: annotation,bioinformatics,genome
Classifier: Development Status :: 4 - Beta
Classifier: Intended Audience :: Science/Research
Classifier: License :: OSI Approved :: BSD License
Classifier: Operating System :: Unix
Classifier: Programming Language :: Python
Classifier: Topic :: Scientific/Engineering :: Bio-Informatics
Requires-Python: >=3.7.0
Requires-Dist: buscolite>=25.4.24
Requires-Dist: gapmm2>=25.4.13
Requires-Dist: gb-io>=0.3.2
Requires-Dist: gfftk>=25.6.10
Requires-Dist: json-repair
Requires-Dist: mappy
Requires-Dist: natsort
Requires-Dist: numpy
Requires-Dist: pyfastx>=2.0.0
Requires-Dist: pyhmmer>=0.10.15
Requires-Dist: pytantan
Requires-Dist: requests
